repository_cloner/__init__.py
repository_cloner/actions.py
repository_cloner/cli.py
repository_cloner/cloner.py
repository_cloner/config.py
repository_cloner/context.py
repository_cloner/provider.py
repository_cloner/sync.py
repository_cloner-0.2.0.dist-info/LICENSE
repository_cloner-0.2.0.dist-info/METADATA
repository_cloner-0.2.0.dist-info/WHEEL
repository_cloner-0.2.0.dist-info/entry_points.txt
repository_cloner-0.2.0.dist-info/RECORD
